knotr-0.4.1.dist-info/DESCRIPTION.rst
knotr-0.4.1.dist-info/METADATA
knotr-0.4.1.dist-info/RECORD
knotr-0.4.1.dist-info/WHEEL
knotr-0.4.1.dist-info/entry_points.txt
knotr-0.4.1.dist-info/metadata.json
knotr-0.4.1.dist-info/top_level.txt
stitch/__init__.py
stitch/__main__.py
stitch/_version.py
stitch/cli.py
stitch/exc.py
stitch/options.py
stitch/parser.py
stitch/stitch.py
stitch/static/default.css
